zaim/__init__.py
zaim/api.py
zaim/extended_api.py
zaim-0.2.3.data/scripts/zaim
zaim-0.2.3.dist-info/METADATA
zaim-0.2.3.dist-info/RECORD
zaim-0.2.3.dist-info/WHEEL
zaim-0.2.3.dist-info/top_level.txt
