Metadata-Version: 2.1
Name: zaim
Version: 0.2.3
Summary: Python bindings for the Zaim API
Home-page: https://github.com/hiromu2000/zaim
Author: Hiromu
Author-email: hiromu2000@hotmail.com
License: MIT
Keywords: zaim api
Platform: UNKNOWN
Classifier: Development Status :: 4 - Beta
Classifier: Intended Audience :: Developers
Classifier: Topic :: Office/Business :: Financial :: Accounting
Classifier: License :: OSI Approved :: MIT License
Classifier: Programming Language :: Python :: 2.7
Classifier: Programming Language :: Python :: 3.6
Classifier: Programming Language :: Python :: 3.7
Requires-Dist: requests
Requires-Dist: requests-oauthlib
Requires-Dist: six
Requires-Dist: future
Requires-Dist: tabulate
